[{"name":"mattetti/ruby-on-rails-tmbundle","tags_url":0,"forks_url":0,"stargazers_url":4,"contributors_url":1,"subscribers_url":1,"commits_url":14,"downloads_url":0,"issues_url":0,"pulls_url":0,"languages_url":"{\"Ruby\":89664}"},{"name":"lawrencepit/ruby-on-rails-tmbundle","tags_url":0,"forks_url":1,"stargazers_url":4,"contributors_url":13,"subscribers_url":2,"commits_url":178,"downloads_url":0,"issues_url":0,"pulls_url":0,"languages_url":"{\"Ruby\":98858,\"JavaScript\":25082}"},{"name":"grempe/amazon-ec2","tags_url":59,"forks_url":101,"stargazers_url":436,"contributors_url":28,"subscribers_url":13,"commits_url":460,"downloads_url":0,"issues_url":16,"pulls_url":16,"languages_url":"{\"Ruby\":370773}"},{"name":"wayneeseguin/merblogger","tags_url":0,"forks_url":3,"stargazers_url":18,"contributors_url":3,"subscribers_url":5,"commits_url":61,"downloads_url":0,"issues_url":1,"pulls_url":1,"languages_url":"{\"JavaScript\":605642,\"Ruby\":111425}"},{"name":"wayneeseguin/merbtastic","tags_url":0,"forks_url":1,"stargazers_url":4,"contributors_url":0,"subscribers_url":2,"commits_url":1,"downloads_url":0,"issues_url":0,"pulls_url":0,"languages_url":"{}"}]